{
  "unversionedId": "prisma-cloud/api/cspm/config-service-api",
  "id": "prisma-cloud/api/cspm/config-service-api",
  "title": "config-service API",
  "description": "",
  "source": "@site/products/prisma-cloud/api/cspm/config-service-api.info.mdx",
  "sourceDirName": "prisma-cloud/api/cspm",
  "slug": "/prisma-cloud/api/cspm/config-service-api",
  "permalink": "/prisma-cloud/api/cspm/config-service-api",
  "draft": false,
  "editUrl": null,
  "tags": [],
  "version": "current",
  "sidebarPosition": 0,
  "frontMatter": {
    "id": "config-service-api",
    "title": "config-service API",
    "description": "",
    "sidebar_label": "Introduction",
    "sidebar_position": 0,
    "hide_title": true,
    "custom_edit_url": null
  }
}