{
  "unversionedId": "sdwan/api/iot",
  "id": "sdwan/api/iot",
  "title": "IoT",
  "description": "List of APIs used to retrieve IoT specific configuration like device IDs and more.",
  "source": "@site/products/sdwan/api/iot.info.mdx",
  "sourceDirName": "sdwan/api",
  "slug": "/sdwan/api/iot",
  "permalink": "/sdwan/api/iot",
  "draft": false,
  "editUrl": null,
  "tags": [],
  "version": "current",
  "frontMatter": {
    "id": "iot",
    "title": "IoT",
    "description": "List of APIs used to retrieve IoT specific configuration like device IDs and more.",
    "sidebar_label": "IoT",
    "hide_title": true,
    "custom_edit_url": null
  },
  "sidebar": "sdwan_unified",
  "previous": {
    "title": "Update IPFIX Site Prefix Association (v2.0)",
    "permalink": "/sdwan/api/put-sdwan-v-2-0-api-sites-site-id-ipfixlocalprefixes-prefix-id"
  },
  "next": {
    "title": "Get Device ID Profiles (v2.0)",
    "permalink": "/sdwan/api/post-sdwan-v-2-0-api-deviceidconfigs-query"
  }
}