{
  "unversionedId": "sase/docs/service-accounts",
  "id": "sase/docs/service-accounts",
  "title": "Service Accounts",
  "description": "Service Accounts are used to obtain access tokens and limit access to SASE APIs.",
  "source": "@site/products/sase/docs/service-accounts.mdx",
  "sourceDirName": "sase/docs",
  "slug": "/sase/docs/service-accounts",
  "permalink": "/sase/docs/service-accounts",
  "draft": false,
  "editUrl": "https://github.com/PaloAltoNetworks/pan.dev/tree/master/products/sase/docs/service-accounts.mdx",
  "tags": [],
  "version": "current",
  "frontMatter": {
    "id": "service-accounts",
    "title": "Service Accounts",
    "description": "Service Accounts are used to obtain access tokens and limit access to SASE APIs.",
    "hide_title": false,
    "hide_table_of_contents": false,
    "keywords": [
      "sase"
    ]
  },
  "sidebar": "sase_docs",
  "previous": {
    "title": "Tenant Service Groups",
    "permalink": "/sase/docs/tenant-service-groups"
  },
  "next": {
    "title": "Roles Overview",
    "permalink": "/sase/docs/roles"
  }
}